crosper_fonseka_package/__init__.py
crosper_fonseka_package/my_sub_module/__init__.py
crosper_fonseka_package/my_sub_module/utils.py
crosper_fonseka_package-0.1.0.dist-info/LICENSE
crosper_fonseka_package-0.1.0.dist-info/METADATA
crosper_fonseka_package-0.1.0.dist-info/WHEEL
crosper_fonseka_package-0.1.0.dist-info/top_level.txt
crosper_fonseka_package-0.1.0.dist-info/RECORD
